NativDebugging/BitsLimitedInteger.py
NativDebugging/DebuggerBase.py
NativDebugging/DumpBase.py
NativDebugging/GUIDisplayBase.py
NativDebugging/Interfaces.py
NativDebugging/MemReaderBase.py
NativDebugging/ObjectWithStream.py
NativDebugging/QtWidgets.py
NativDebugging/RecursiveFind.py
NativDebugging/Utilities.py
NativDebugging/__init__.py
NativDebugging/File/FileReader.py
NativDebugging/File/__init__.py
NativDebugging/Linux/PtraceMemReader.py
NativDebugging/Linux/SharedMemReader.py
NativDebugging/Linux/__init__.py
NativDebugging/MemoryDump/MiniDump.py
NativDebugging/MemoryDump/Reader.py
NativDebugging/MemoryDump/__init__.py
NativDebugging/Patterns/Finder.py
NativDebugging/Patterns/Macho.py
NativDebugging/Patterns/PDB.py
NativDebugging/Patterns/PE.py
NativDebugging/Patterns/__init__.py
NativDebugging/Unix/MemoryReaderCommunicator.py
NativDebugging/Unix/__init__.py
NativDebugging/Win32/BreakPoint.py
NativDebugging/Win32/Debugger.py
NativDebugging/Win32/DetoursWrapper.py
NativDebugging/Win32/DifferentialSearch.py
NativDebugging/Win32/DllInfo.py
NativDebugging/Win32/ExternalMemoryReader.py
NativDebugging/Win32/GetPdb.py
NativDebugging/Win32/InjectDll.py
NativDebugging/Win32/MemReaderBaseWin.py
NativDebugging/Win32/MemReaderOverRPyC.py
NativDebugging/Win32/MemoryMap.py
NativDebugging/Win32/MemoryReader.py
NativDebugging/Win32/ProcessCreateAndAttach.py
NativDebugging/Win32/SelfInspector.py
NativDebugging/Win32/SharedMemReader.py
NativDebugging/Win32/Symbols.py
NativDebugging/Win32/Win32Structs.py
NativDebugging/Win32/Win32Utilities.py
NativDebugging/Win32/__init__.py
NativDebugging-39.data/data/NativDebugging.pth
NativDebugging-39.data/data/NativDebugging/Win32/DetoursAMD64.dll
NativDebugging-39.data/data/NativDebugging/Win32/Detoursx86.dll
NativDebugging-39.data/data/NativDebugging/Win32/memReaderAMD64.exe
NativDebugging-39.data/data/NativDebugging/Win32/memReaderIa64.exe
NativDebugging-39.data/data/NativDebugging/Win32/memReaderx86.exe
NativDebugging-39.dist-info/LICENSE
NativDebugging-39.dist-info/METADATA
NativDebugging-39.dist-info/WHEEL
NativDebugging-39.dist-info/top_level.txt
NativDebugging-39.dist-info/RECORD
