Metadata-Version: 2.1
Name: NativDebugging
Version: 39
Summary: Debugging tools for many platforms
Home-page: https://github.com/assafnativ/NativDebugging
Author: Assaf Nativ
Author-email: Nativ.Assaf@gmail.com
License: LGPLv3
Keywords: debugger,memory,patterns,research,lowlevel,native
Platform: UNKNOWN
Requires-Dist: future
Requires-Dist: rpyc
Requires-Dist: distorm3
Requires-Dist: QtWidgets
Requires-Dist: pywin32 ; platform_system == "Windows"
